Metadata-Version: 2.1
Name: myregr
Version: 0.0.1
Summary: a regression tool
Home-page: 
Author: Venkat B S
Author-email: venkatbs2003@gmail.com
License: MIT
Keywords: regression
Classifier: Development Status :: 5 - Production/Stable
Classifier: Intended Audience :: Education
Classifier: License :: OSI Approved :: MIT License
Classifier: Programming Language :: Python :: 3
License-File: LICENSE.txt
